{
  "generator-jhipster": {
    "promptValues": {
      "packageName": "com.mycompany.myapp"
    },
    "jhipsterVersion": "6.0.1",
    "applicationType": "monolith",
    "baseName": "TenderFlow",
    "packageName": "com.mycompany.myapp",
    "packageFolder": "com/mycompany/myapp",
    "serverPort": "8080",
    "authenticationType": "jwt",
    "cacheProvider": "hazelcast",
    "enableHibernateCache": true,
    "websocket": "spring-websocket",
    "databaseType": "sql",
    "devDatabaseType": "h2Disk",
    "prodDatabaseType": "mysql",
    "searchEngine": false,
    "messageBroker": false,
    "serviceDiscoveryType": false,
    "buildTool": "gradle",
    "enableSwaggerCodegen": false,
    "jwtSecretKey": "ZTc0MTgzYzA2M2FiMDAzNzZjMDRkZWEzN2QxZWI5MmM0ZGQ5ZTliOThkYjExNDFmMGU5MTU1MTNhOTQ1NDJkN2NmNDA1ODIyMzdlODllY2Y0NjVlMDIxOTVlNWYxMGFhOTIwMTI5NDQwZGY2YWU2MWFhMDk1ZTYwMDViYjY1NTM=",
    "clientFramework": "angularX",
    "clientTheme": "cerulean",
    "clientThemeVariant": "primary",
    "useSass": true,
    "clientPackageManager": "npm",
    "testFrameworks": ["gatling", "protractor"],
    "jhiPrefix": "jhi",
    "entitySuffix": "",
    "dtoSuffix": "DTO",
    "otherModules": [],
    "enableTranslation": false
  }
}
